grant/__init__.py
grant/grant_select.py
grant/readlist.py
grant-1.2.6.dist-info/METADATA
grant-1.2.6.dist-info/WHEEL
grant-1.2.6.dist-info/top_level.txt
grant-1.2.6.dist-info/RECORD
