Metadata-Version: 2.1
Name: grant
Version: 1.2.6
Summary: Test publish own pypi.
Home-page: https://github.com/js8976/oracleusergrant
Author: jiangshuo
Author-email: jiangshuo-ghq@sinosig.com
License: MIT
Keywords: jiangshuo6
Platform: UNKNOWN
Classifier: Intended Audience :: Developers
Classifier: License :: OSI Approved :: MIT License
Classifier: Natural Language :: English
Classifier: Programming Language :: Python
Classifier: Programming Language :: Python :: Implementation
Classifier: Programming Language :: Python :: 3.4
Classifier: Programming Language :: Python :: 3.5
Classifier: Programming Language :: Python :: 3.6
Classifier: Programming Language :: Python :: 3.7
Classifier: Programming Language :: Python :: 3.8
Classifier: Programming Language :: Python :: 3.9
Classifier: Topic :: Utilities
Requires-Python: >=3.4.0
Requires-Dist: cx-Oracle
